procountor/__init__.py
procountor/api_methods.py
procountor/client.py
Procountor-2.4.0.dist-info/AUTHORS.rst
Procountor-2.4.0.dist-info/LICENCE
Procountor-2.4.0.dist-info/METADATA
Procountor-2.4.0.dist-info/WHEEL
Procountor-2.4.0.dist-info/top_level.txt
Procountor-2.4.0.dist-info/RECORD
