Metadata-Version: 2.1
Name: Procountor
Version: 2.4.0
Summary: Python library for calling Procountor REST API
Home-page: https://github.com/vilkasgroup/Procountor
Author: Joonas Maliniemi
Author-email: joonas@vilkas.fi
License: MIT license
Keywords: procountor
Classifier: Development Status :: 2 - Pre-Alpha
Classifier: Intended Audience :: Developers
Classifier: License :: OSI Approved :: MIT License
Classifier: Natural Language :: English
Classifier: Programming Language :: Python :: 2.7
Classifier: Programming Language :: Python :: 3.6
License-File: LICENCE
License-File: AUTHORS.rst
Requires-Dist: requests
Requires-Dist: requests-toolbelt
